flumes/__init__.py
flumes/agent.py
flumes/aio_agent.py
flumes/aio_client.py
flumes/client.py
flumes/exceptions.py
flumes/logger.py
flumes/models.py
flumes/transport.py
flumes/policy/__init__.py
flumes/utils/__init__.py
flumes/utils/openai_wrapper.py
flumes/utils/retry.py
flumes_ai-0.2.3.dist-info/METADATA
flumes_ai-0.2.3.dist-info/WHEEL
flumes_ai-0.2.3.dist-info/licenses/LICENSE
flumes_ai-0.2.3.dist-info/RECORD
