Metadata-Version: 2.4
Name: flumes-ai
Version: 0.2.3
Summary: Flumes – unified memory infrastructure SDK for AI agents (Python)
Project-URL: Homepage, https://www.flumes.ai
Project-URL: Source, https://github.com/alex-n-a/flumes-ai-sdk
Author-email: Flumes AI <support@flumes.ai>
License: MIT
License-File: LICENSE
Requires-Python: >=3.9
Requires-Dist: httpx<1,>=0.27
Requires-Dist: pydantic>=2
Requires-Dist: typing-extensions; python_version < '3.11'
Provides-Extra: agent
Requires-Dist: openai>=1; extra == 'agent'
Provides-Extra: dev
Requires-Dist: build; extra == 'dev'
Requires-Dist: hatchling; extra == 'dev'
Requires-Dist: pytest-httpx>=0.30; extra == 'dev'
Requires-Dist: pytest>=8; extra == 'dev'
Requires-Dist: ruff>=0.4; extra == 'dev'
Requires-Dist: twine; extra == 'dev'
